<SUF70Messages>
<Language>
<Name>Romanian</Name>
<Default>0</Default>
<Primary>24</Primary>
<Secondary>
</Secondary>
</Language>
<Messages>
<IDS_WINDOW_TITLE>Instalare %ProductName%</IDS_WINDOW_TITLE>
<IDS_HEADER_TEXT>Executare actiuni</IDS_HEADER_TEXT>
<IDS_SUBHEADER_TEXT>Va rugam asteptati...</IDS_SUBHEADER_TEXT>
<IDS_CTRL_BUTTON_CANCEL>&Anulare</IDS_CTRL_BUTTON_CANCEL>
<IDS_CTRL_STATICTEXT_TOPINSTRUCTIONS>Va rugam asteptati in timp ce unele actiuni sunt executate pe sistemul dvs.</IDS_CTRL_STATICTEXT_TOPINSTRUCTIONS>
<IDS_CTRL_STATICTEXT_LABEL_01>Progres Unu</IDS_CTRL_STATICTEXT_LABEL_01>
<IDS_CTRL_STATICTEXT_LABEL_02>Executare actiuni...</IDS_CTRL_STATICTEXT_LABEL_02>
<IDS_CTRL_PROGRESS_BAR_01/>
<IDS_CTRL_STATICTEXT_LABEL_03>Progres Doi</IDS_CTRL_STATICTEXT_LABEL_03>
<IDS_CTRL_STATICTEXT_LABEL_04>Executare actiuni...</IDS_CTRL_STATICTEXT_LABEL_04>
<IDS_CTRL_PROGRESS_BAR_02/>
</Messages>
</SUF70Messages>
